{"version":"tree-0.1","tree":{"id":"App","path":"","constructInfo":{"fqn":"aws-cdk-lib.App","version":"2.240.0"},"children":{"SpendlyStack":{"id":"SpendlyStack","path":"SpendlyStack","constructInfo":{"fqn":"aws-cdk-lib.Stack","version":"2.240.0"},"children":{"SpendlyVpc":{"id":"SpendlyVpc","path":"SpendlyStack/SpendlyVpc","constructInfo":{"fqn":"aws-cdk-lib.aws_ec2.Vpc","version":"2.240.0"},"children":{"Resource":{"id":"Resource","path":"SpendlyStack/SpendlyVpc/Resource","constructInfo":{"fqn":"aws-cdk-lib.aws_ec2.CfnVPC","version":"2.240.0"},"attributes":{"aws:cdk:cloudformation:type":"AWS::EC2::VPC","aws:cdk:cloudformation:props":{"cidrBlock":"10.0.0.0/16","enableDnsHostnames":true,"enableDnsSupport":true,"instanceTenancy":"default","tags":[{"key":"Name","value":"SpendlyStack/SpendlyVpc"}]}}},"PublicSubnet1":{"id":"PublicSubnet1","path":"SpendlyStack/SpendlyVpc/PublicSubnet1","constructInfo":{"fqn":"aws-cdk-lib.aws_ec2.PublicSubnet","version":"2.240.0"},"children":{"Subnet":{"id":"Subnet","path":"SpendlyStack/SpendlyVpc/PublicSubnet1/Subnet","constructInfo":{"fqn":"aws-cdk-lib.aws_ec2.CfnSubnet","version":"2.240.0"},"attributes":{"aws:cdk:cloudformation:type":"AWS::EC2::Subnet","aws:cdk:cloudformation:props":{"availabilityZone":"us-east-1a","cidrBlock":"10.0.0.0/24","mapPublicIpOnLaunch":true,"tags":[{"key":"aws-cdk:subnet-name","value":"Public"},{"key":"aws-cdk:subnet-type","value":"Public"},{"key":"Name","value":"SpendlyStack/SpendlyVpc/PublicSubnet1"}],"vpcId":{"Ref":"SpendlyVpcAA2F8862"}}}},"Acl":{"id":"Acl","path":"SpendlyStack/SpendlyVpc/PublicSubnet1/Acl","constructInfo":{"fqn":"aws-cdk-lib.Resource","version":"2.240.0"}},"RouteTable":{"id":"RouteTable","path":"SpendlyStack/SpendlyVpc/PublicSubnet1/RouteTable","constructInfo":{"fqn":"aws-cdk-lib.aws_ec2.CfnRouteTable","version":"2.240.0"},"attributes":{"aws:cdk:cloudformation:type":"AWS::EC2::RouteTable","aws:cdk:cloudformation:props":{"tags":[{"key":"Name","value":"SpendlyStack/SpendlyVpc/PublicSubnet1"}],"vpcId":{"Ref":"SpendlyVpcAA2F8862"}}}},"RouteTableAssociation":{"id":"RouteTableAssociation","path":"SpendlyStack/SpendlyVpc/PublicSubnet1/RouteTableAssociation","constructInfo":{"fqn":"aws-cdk-lib.aws_ec2.CfnSubnetRouteTableAssociation","version":"2.240.0"},"attributes":{"aws:cdk:cloudformation:type":"AWS::EC2::SubnetRouteTableAssociation","aws:cdk:cloudformation:props":{"routeTableId":{"Ref":"SpendlyVpcPublicSubnet1RouteTableE8051A8D"},"subnetId":{"Ref":"SpendlyVpcPublicSubnet1Subnet2F7967E4"}}}},"DefaultRoute":{"id":"DefaultRoute","path":"SpendlyStack/SpendlyVpc/PublicSubnet1/DefaultRoute","constructInfo":{"fqn":"aws-cdk-lib.aws_ec2.CfnRoute","version":"2.240.0"},"attributes":{"aws:cdk:cloudformation:type":"AWS::EC2::Route","aws:cdk:cloudformation:props":{"destinationCidrBlock":"0.0.0.0/0","gatewayId":{"Ref":"SpendlyVpcIGWF3CACAD3"},"routeTableId":{"Ref":"SpendlyVpcPublicSubnet1RouteTableE8051A8D"}}}},"EIP":{"id":"EIP","path":"SpendlyStack/SpendlyVpc/PublicSubnet1/EIP","constructInfo":{"fqn":"aws-cdk-lib.aws_ec2.CfnEIP","version":"2.240.0"},"attributes":{"aws:cdk:cloudformation:type":"AWS::EC2::EIP","aws:cdk:cloudformation:props":{"domain":"vpc","tags":[{"key":"Name","value":"SpendlyStack/SpendlyVpc/PublicSubnet1"}]}}},"NATGateway":{"id":"NATGateway","path":"SpendlyStack/SpendlyVpc/PublicSubnet1/NATGateway","constructInfo":{"fqn":"aws-cdk-lib.aws_ec2.CfnNatGateway","version":"2.240.0"},"attributes":{"aws:cdk:cloudformation:type":"AWS::EC2::NatGateway","aws:cdk:cloudformation:props":{"allocationId":{"Fn::GetAtt":["SpendlyVpcPublicSubnet1EIP5913246F","AllocationId"]},"subnetId":{"Ref":"SpendlyVpcPublicSubnet1Subnet2F7967E4"},"tags":[{"key":"Name","value":"SpendlyStack/SpendlyVpc/PublicSubnet1"}]}}}}},"PublicSubnet2":{"id":"PublicSubnet2","path":"SpendlyStack/SpendlyVpc/PublicSubnet2","constructInfo":{"fqn":"aws-cdk-lib.aws_ec2.PublicSubnet","version":"2.240.0"},"children":{"Subnet":{"id":"Subnet","path":"SpendlyStack/SpendlyVpc/PublicSubnet2/Subnet","constructInfo":{"fqn":"aws-cdk-lib.aws_ec2.CfnSubnet","version":"2.240.0"},"attributes":{"aws:cdk:cloudformation:type":"AWS::EC2::Subnet","aws:cdk:cloudformation:props":{"availabilityZone":"us-east-1b","cidrBlock":"10.0.1.0/24","mapPublicIpOnLaunch":true,"tags":[{"key":"aws-cdk:subnet-name","value":"Public"},{"key":"aws-cdk:subnet-type","value":"Public"},{"key":"Name","value":"SpendlyStack/SpendlyVpc/PublicSubnet2"}],"vpcId":{"Ref":"SpendlyVpcAA2F8862"}}}},"Acl":{"id":"Acl","path":"SpendlyStack/SpendlyVpc/PublicSubnet2/Acl","constructInfo":{"fqn":"aws-cdk-lib.Resource","version":"2.240.0"}},"RouteTable":{"id":"RouteTable","path":"SpendlyStack/SpendlyVpc/PublicSubnet2/RouteTable","constructInfo":{"fqn":"aws-cdk-lib.aws_ec2.CfnRouteTable","version":"2.240.0"},"attributes":{"aws:cdk:cloudformation:type":"AWS::EC2::RouteTable","aws:cdk:cloudformation:props":{"tags":[{"key":"Name","value":"SpendlyStack/SpendlyVpc/PublicSubnet2"}],"vpcId":{"Ref":"SpendlyVpcAA2F8862"}}}},"RouteTableAssociation":{"id":"RouteTableAssociation","path":"SpendlyStack/SpendlyVpc/PublicSubnet2/RouteTableAssociation","constructInfo":{"fqn":"aws-cdk-lib.aws_ec2.CfnSubnetRouteTableAssociation","version":"2.240.0"},"attributes":{"aws:cdk:cloudformation:type":"AWS::EC2::SubnetRouteTableAssociation","aws:cdk:cloudformation:props":{"routeTableId":{"Ref":"SpendlyVpcPublicSubnet2RouteTable0548BDA7"},"subnetId":{"Ref":"SpendlyVpcPublicSubnet2SubnetF79DECBC"}}}},"DefaultRoute":{"id":"DefaultRoute","path":"SpendlyStack/SpendlyVpc/PublicSubnet2/DefaultRoute","constructInfo":{"fqn":"aws-cdk-lib.aws_ec2.CfnRoute","version":"2.240.0"},"attributes":{"aws:cdk:cloudformation:type":"AWS::EC2::Route","aws:cdk:cloudformation:props":{"destinationCidrBlock":"0.0.0.0/0","gatewayId":{"Ref":"SpendlyVpcIGWF3CACAD3"},"routeTableId":{"Ref":"SpendlyVpcPublicSubnet2RouteTable0548BDA7"}}}}}},"PrivateSubnet1":{"id":"PrivateSubnet1","path":"SpendlyStack/SpendlyVpc/PrivateSubnet1","constructInfo":{"fqn":"aws-cdk-lib.aws_ec2.PrivateSubnet","version":"2.240.0"},"children":{"Subnet":{"id":"Subnet","path":"SpendlyStack/SpendlyVpc/PrivateSubnet1/Subnet","constructInfo":{"fqn":"aws-cdk-lib.aws_ec2.CfnSubnet","version":"2.240.0"},"attributes":{"aws:cdk:cloudformation:type":"AWS::EC2::Subnet","aws:cdk:cloudformation:props":{"availabilityZone":"us-east-1a","cidrBlock":"10.0.2.0/24","mapPublicIpOnLaunch":false,"tags":[{"key":"aws-cdk:subnet-name","value":"Private"},{"key":"aws-cdk:subnet-type","value":"Private"},{"key":"Name","value":"SpendlyStack/SpendlyVpc/PrivateSubnet1"}],"vpcId":{"Ref":"SpendlyVpcAA2F8862"}}}},"Acl":{"id":"Acl","path":"SpendlyStack/SpendlyVpc/PrivateSubnet1/Acl","constructInfo":{"fqn":"aws-cdk-lib.Resource","version":"2.240.0"}},"RouteTable":{"id":"RouteTable","path":"SpendlyStack/SpendlyVpc/PrivateSubnet1/RouteTable","constructInfo":{"fqn":"aws-cdk-lib.aws_ec2.CfnRouteTable","version":"2.240.0"},"attributes":{"aws:cdk:cloudformation:type":"AWS::EC2::RouteTable","aws:cdk:cloudformation:props":{"tags":[{"key":"Name","value":"SpendlyStack/SpendlyVpc/PrivateSubnet1"}],"vpcId":{"Ref":"SpendlyVpcAA2F8862"}}}},"RouteTableAssociation":{"id":"RouteTableAssociation","path":"SpendlyStack/SpendlyVpc/PrivateSubnet1/RouteTableAssociation","constructInfo":{"fqn":"aws-cdk-lib.aws_ec2.CfnSubnetRouteTableAssociation","version":"2.240.0"},"attributes":{"aws:cdk:cloudformation:type":"AWS::EC2::SubnetRouteTableAssociation","aws:cdk:cloudformation:props":{"routeTableId":{"Ref":"SpendlyVpcPrivateSubnet1RouteTableF5D35CF6"},"subnetId":{"Ref":"SpendlyVpcPrivateSubnet1SubnetF34C9517"}}}},"DefaultRoute":{"id":"DefaultRoute","path":"SpendlyStack/SpendlyVpc/PrivateSubnet1/DefaultRoute","constructInfo":{"fqn":"aws-cdk-lib.aws_ec2.CfnRoute","version":"2.240.0"},"attributes":{"aws:cdk:cloudformation:type":"AWS::EC2::Route","aws:cdk:cloudformation:props":{"destinationCidrBlock":"0.0.0.0/0","natGatewayId":{"Ref":"SpendlyVpcPublicSubnet1NATGateway15E270A7"},"routeTableId":{"Ref":"SpendlyVpcPrivateSubnet1RouteTableF5D35CF6"}}}}}},"PrivateSubnet2":{"id":"PrivateSubnet2","path":"SpendlyStack/SpendlyVpc/PrivateSubnet2","constructInfo":{"fqn":"aws-cdk-lib.aws_ec2.PrivateSubnet","version":"2.240.0"},"children":{"Subnet":{"id":"Subnet","path":"SpendlyStack/SpendlyVpc/PrivateSubnet2/Subnet","constructInfo":{"fqn":"aws-cdk-lib.aws_ec2.CfnSubnet","version":"2.240.0"},"attributes":{"aws:cdk:cloudformation:type":"AWS::EC2::Subnet","aws:cdk:cloudformation:props":{"availabilityZone":"us-east-1b","cidrBlock":"10.0.3.0/24","mapPublicIpOnLaunch":false,"tags":[{"key":"aws-cdk:subnet-name","value":"Private"},{"key":"aws-cdk:subnet-type","value":"Private"},{"key":"Name","value":"SpendlyStack/SpendlyVpc/PrivateSubnet2"}],"vpcId":{"Ref":"SpendlyVpcAA2F8862"}}}},"Acl":{"id":"Acl","path":"SpendlyStack/SpendlyVpc/PrivateSubnet2/Acl","constructInfo":{"fqn":"aws-cdk-lib.Resource","version":"2.240.0"}},"RouteTable":{"id":"RouteTable","path":"SpendlyStack/SpendlyVpc/PrivateSubnet2/RouteTable","constructInfo":{"fqn":"aws-cdk-lib.aws_ec2.CfnRouteTable","version":"2.240.0"},"attributes":{"aws:cdk:cloudformation:type":"AWS::EC2::RouteTable","aws:cdk:cloudformation:props":{"tags":[{"key":"Name","value":"SpendlyStack/SpendlyVpc/PrivateSubnet2"}],"vpcId":{"Ref":"SpendlyVpcAA2F8862"}}}},"RouteTableAssociation":{"id":"RouteTableAssociation","path":"SpendlyStack/SpendlyVpc/PrivateSubnet2/RouteTableAssociation","constructInfo":{"fqn":"aws-cdk-lib.aws_ec2.CfnSubnetRouteTableAssociation","version":"2.240.0"},"attributes":{"aws:cdk:cloudformation:type":"AWS::EC2::SubnetRouteTableAssociation","aws:cdk:cloudformation:props":{"routeTableId":{"Ref":"SpendlyVpcPrivateSubnet2RouteTable3DBA9A25"},"subnetId":{"Ref":"SpendlyVpcPrivateSubnet2Subnet8C4D6774"}}}},"DefaultRoute":{"id":"DefaultRoute","path":"SpendlyStack/SpendlyVpc/PrivateSubnet2/DefaultRoute","constructInfo":{"fqn":"aws-cdk-lib.aws_ec2.CfnRoute","version":"2.240.0"},"attributes":{"aws:cdk:cloudformation:type":"AWS::EC2::Route","aws:cdk:cloudformation:props":{"destinationCidrBlock":"0.0.0.0/0","natGatewayId":{"Ref":"SpendlyVpcPublicSubnet1NATGateway15E270A7"},"routeTableId":{"Ref":"SpendlyVpcPrivateSubnet2RouteTable3DBA9A25"}}}}}},"IGW":{"id":"IGW","path":"SpendlyStack/SpendlyVpc/IGW","constructInfo":{"fqn":"aws-cdk-lib.aws_ec2.CfnInternetGateway","version":"2.240.0"},"attributes":{"aws:cdk:cloudformation:type":"AWS::EC2::InternetGateway","aws:cdk:cloudformation:props":{"tags":[{"key":"Name","value":"SpendlyStack/SpendlyVpc"}]}}},"VPCGW":{"id":"VPCGW","path":"SpendlyStack/SpendlyVpc/VPCGW","constructInfo":{"fqn":"aws-cdk-lib.aws_ec2.CfnVPCGatewayAttachment","version":"2.240.0"},"attributes":{"aws:cdk:cloudformation:type":"AWS::EC2::VPCGatewayAttachment","aws:cdk:cloudformation:props":{"internetGatewayId":{"Ref":"SpendlyVpcIGWF3CACAD3"},"vpcId":{"Ref":"SpendlyVpcAA2F8862"}}}}}},"SpendlySecrets":{"id":"SpendlySecrets","path":"SpendlyStack/SpendlySecrets","constructInfo":{"fqn":"aws-cdk-lib.aws_secretsmanager.Secret","version":"2.240.0"},"children":{"Resource":{"id":"Resource","path":"SpendlyStack/SpendlySecrets/Resource","constructInfo":{"fqn":"aws-cdk-lib.aws_secretsmanager.CfnSecret","version":"2.240.0"},"attributes":{"aws:cdk:cloudformation:type":"AWS::SecretsManager::Secret","aws:cdk:cloudformation:props":{"description":"Spendly application secrets","generateSecretString":{"secretStringTemplate":"{\"DATABASE_URL\":\"\",\"SESSION_SECRET\":\"\",\"STRIPE_SECRET_KEY\":\"\",\"STRIPE_WEBHOOK_SECRET\":\"\",\"PAYSTACK_SECRET_KEY\":\"\",\"COGNITO_USER_POOL_ID\":\"\",\"COGNITO_CLIENT_ID\":\"\"}","generateStringKey":"SESSION_SECRET"},"name":"spendly/app-secrets"}}}}},"DbSecurityGroup":{"id":"DbSecurityGroup","path":"SpendlyStack/DbSecurityGroup","constructInfo":{"fqn":"aws-cdk-lib.aws_ec2.SecurityGroup","version":"2.240.0"},"children":{"Resource":{"id":"Resource","path":"SpendlyStack/DbSecurityGroup/Resource","constructInfo":{"fqn":"aws-cdk-lib.aws_ec2.CfnSecurityGroup","version":"2.240.0"},"attributes":{"aws:cdk:cloudformation:type":"AWS::EC2::SecurityGroup","aws:cdk:cloudformation:props":{"groupDescription":"Security group for Spendly RDS","securityGroupEgress":[{"cidrIp":"255.255.255.255/32","description":"Disallow all traffic","ipProtocol":"icmp","fromPort":252,"toPort":86}],"vpcId":{"Ref":"SpendlyVpcAA2F8862"}}}},"from SpendlyStackServiceSecurityGroupC6E7F6D5:5432":{"id":"from SpendlyStackServiceSecurityGroupC6E7F6D5:5432","path":"SpendlyStack/DbSecurityGroup/from SpendlyStackServiceSecurityGroupC6E7F6D5:5432","constructInfo":{"fqn":"aws-cdk-lib.aws_ec2.CfnSecurityGroupIngress","version":"2.240.0"},"attributes":{"aws:cdk:cloudformation:type":"AWS::EC2::SecurityGroupIngress","aws:cdk:cloudformation:props":{"description":"Allow from ECS","fromPort":5432,"groupId":{"Fn::GetAtt":["DbSecurityGroupE9D701AD","GroupId"]},"ipProtocol":"tcp","sourceSecurityGroupId":{"Fn::GetAtt":["ServiceSecurityGroup61DE1A49","GroupId"]},"toPort":5432}}}}},"SpendlyDb":{"id":"SpendlyDb","path":"SpendlyStack/SpendlyDb","constructInfo":{"fqn":"aws-cdk-lib.aws_rds.DatabaseInstance","version":"2.240.0"},"children":{"SubnetGroup":{"id":"SubnetGroup","path":"SpendlyStack/SpendlyDb/SubnetGroup","constructInfo":{"fqn":"aws-cdk-lib.aws_rds.SubnetGroup","version":"2.240.0"},"children":{"Default":{"id":"Default","path":"SpendlyStack/SpendlyDb/SubnetGroup/Default","constructInfo":{"fqn":"aws-cdk-lib.aws_rds.CfnDBSubnetGroup","version":"2.240.0"},"attributes":{"aws:cdk:cloudformation:type":"AWS::RDS::DBSubnetGroup","aws:cdk:cloudformation:props":{"dbSubnetGroupDescription":"Subnet group for SpendlyDb database","subnetIds":[{"Ref":"SpendlyVpcPrivateSubnet1SubnetF34C9517"},{"Ref":"SpendlyVpcPrivateSubnet2Subnet8C4D6774"}]}}}}},"Secret":{"id":"Secret","path":"SpendlyStack/SpendlyDb/Secret","constructInfo":{"fqn":"aws-cdk-lib.aws_rds.DatabaseSecret","version":"2.240.0"},"children":{"Resource":{"id":"Resource","path":"SpendlyStack/SpendlyDb/Secret/Resource","constructInfo":{"fqn":"aws-cdk-lib.aws_secretsmanager.CfnSecret","version":"2.240.0"},"attributes":{"aws:cdk:cloudformation:type":"AWS::SecretsManager::Secret","aws:cdk:cloudformation:props":{"description":{"Fn::Join":["",["Generated by the CDK for stack: ",{"Ref":"AWS::StackName"}]]},"generateSecretString":{"passwordLength":30,"secretStringTemplate":"{\"username\":\"spendly_admin\"}","generateStringKey":"password","excludeCharacters":" %+~`#$&*()|[]{}:;<>?!'/@\"\\"},"name":"spendly/db-credentials"}}},"Attachment":{"id":"Attachment","path":"SpendlyStack/SpendlyDb/Secret/Attachment","constructInfo":{"fqn":"aws-cdk-lib.aws_secretsmanager.SecretTargetAttachment","version":"2.240.0"},"children":{"Resource":{"id":"Resource","path":"SpendlyStack/SpendlyDb/Secret/Attachment/Resource","constructInfo":{"fqn":"aws-cdk-lib.aws_secretsmanager.CfnSecretTargetAttachment","version":"2.240.0"},"attributes":{"aws:cdk:cloudformation:type":"AWS::SecretsManager::SecretTargetAttachment","aws:cdk:cloudformation:props":{"secretId":{"Ref":"SpendlyStackSpendlyDbSecretE92A79D43fdaad7efa858a3daf9490cf0a702aeb"},"targetId":{"Ref":"SpendlyDb2DBAC283"},"targetType":"AWS::RDS::DBInstance"}}}}}}},"Resource":{"id":"Resource","path":"SpendlyStack/SpendlyDb/Resource","constructInfo":{"fqn":"aws-cdk-lib.aws_rds.CfnDBInstance","version":"2.240.0"},"attributes":{"aws:cdk:cloudformation:type":"AWS::RDS::DBInstance","aws:cdk:cloudformation:props":{"allocatedStorage":"20","backupRetentionPeriod":7,"copyTagsToSnapshot":true,"dbInstanceClass":"db.t3.micro","dbName":"spendly","dbSubnetGroupName":{"Ref":"SpendlyDbSubnetGroup30B9BE15"},"deletionProtection":true,"engine":"postgres","engineVersion":"16.4","masterUsername":"spendly_admin","masterUserPassword":{"Fn::Join":["",["{{resolve:secretsmanager:",{"Ref":"SpendlyStackSpendlyDbSecretE92A79D43fdaad7efa858a3daf9490cf0a702aeb"},":SecretString:password::}}"]]},"maxAllocatedStorage":100,"multiAz":false,"publiclyAccessible":false,"storageEncrypted":true,"storageType":"gp2","vpcSecurityGroups":[{"Fn::GetAtt":["DbSecurityGroupE9D701AD","GroupId"]}]}}}}},"SpendlyRepo":{"id":"SpendlyRepo","path":"SpendlyStack/SpendlyRepo","constructInfo":{"fqn":"aws-cdk-lib.aws_ecr.Repository","version":"2.240.0"},"children":{"Resource":{"id":"Resource","path":"SpendlyStack/SpendlyRepo/Resource","constructInfo":{"fqn":"aws-cdk-lib.aws_ecr.CfnRepository","version":"2.240.0"},"attributes":{"aws:cdk:cloudformation:type":"AWS::ECR::Repository","aws:cdk:cloudformation:props":{"lifecyclePolicy":{"lifecyclePolicyText":"{\"rules\":[{\"rulePriority\":1,\"description\":\"Keep last 10 images\",\"selection\":{\"tagStatus\":\"any\",\"countType\":\"imageCountMoreThan\",\"countNumber\":10},\"action\":{\"type\":\"expire\"}}]}"},"repositoryName":"spendly"}}}}},"SpendlyCluster":{"id":"SpendlyCluster","path":"SpendlyStack/SpendlyCluster","constructInfo":{"fqn":"aws-cdk-lib.aws_ecs.Cluster","version":"2.240.0"},"children":{"Resource":{"id":"Resource","path":"SpendlyStack/SpendlyCluster/Resource","constructInfo":{"fqn":"aws-cdk-lib.aws_ecs.CfnCluster","version":"2.240.0"},"attributes":{"aws:cdk:cloudformation:type":"AWS::ECS::Cluster","aws:cdk:cloudformation:props":{"clusterName":"spendly","clusterSettings":[{"name":"containerInsights","value":"enabled"}]}}}}},"SpendlyTaskRole":{"id":"SpendlyTaskRole","path":"SpendlyStack/SpendlyTaskRole","constructInfo":{"fqn":"aws-cdk-lib.aws_iam.Role","version":"2.240.0"},"children":{"Resource":{"id":"Resource","path":"SpendlyStack/SpendlyTaskRole/Resource","constructInfo":{"fqn":"aws-cdk-lib.aws_iam.CfnRole","version":"2.240.0"},"attributes":{"aws:cdk:cloudformation:type":"AWS::IAM::Role","aws:cdk:cloudformation:props":{"assumeRolePolicyDocument":{"Statement":[{"Action":"sts:AssumeRole","Effect":"Allow","Principal":{"Service":"ecs-tasks.amazonaws.com"}}],"Version":"2012-10-17"},"description":"Spendly ECS task role"}}},"DefaultPolicy":{"id":"DefaultPolicy","path":"SpendlyStack/SpendlyTaskRole/DefaultPolicy","constructInfo":{"fqn":"aws-cdk-lib.aws_iam.Policy","version":"2.240.0"},"children":{"Resource":{"id":"Resource","path":"SpendlyStack/SpendlyTaskRole/DefaultPolicy/Resource","constructInfo":{"fqn":"aws-cdk-lib.aws_iam.CfnPolicy","version":"2.240.0"},"attributes":{"aws:cdk:cloudformation:type":"AWS::IAM::Policy","aws:cdk:cloudformation:props":{"policyDocument":{"Statement":[{"Action":["ses:SendEmail","ses:SendRawEmail"],"Effect":"Allow","Resource":"*"},{"Action":"sns:Publish","Effect":"Allow","Resource":"*"},{"Action":["secretsmanager:GetSecretValue","secretsmanager:DescribeSecret"],"Effect":"Allow","Resource":{"Ref":"SpendlySecrets32749308"}},{"Action":["secretsmanager:GetSecretValue","secretsmanager:DescribeSecret"],"Effect":"Allow","Resource":{"Ref":"SpendlyDbSecretAttachmentC18EF2DB"}}],"Version":"2012-10-17"},"policyName":"SpendlyTaskRoleDefaultPolicyD4BC9DB9","roles":[{"Ref":"SpendlyTaskRole81FA43D9"}]}}}}}}},"SpendlyTask":{"id":"SpendlyTask","path":"SpendlyStack/SpendlyTask","constructInfo":{"fqn":"aws-cdk-lib.aws_ecs.FargateTaskDefinition","version":"2.240.0"},"children":{"Resource":{"id":"Resource","path":"SpendlyStack/SpendlyTask/Resource","constructInfo":{"fqn":"aws-cdk-lib.aws_ecs.CfnTaskDefinition","version":"2.240.0"},"attributes":{"aws:cdk:cloudformation:type":"AWS::ECS::TaskDefinition","aws:cdk:cloudformation:props":{"containerDefinitions":[{"essential":true,"image":{"Fn::Join":["",[{"Fn::Select":[4,{"Fn::Split":[":",{"Fn::GetAtt":["SpendlyRepo7631E463","Arn"]}]}]},".dkr.ecr.",{"Fn::Select":[3,{"Fn::Split":[":",{"Fn::GetAtt":["SpendlyRepo7631E463","Arn"]}]}]},".",{"Ref":"AWS::URLSuffix"},"/",{"Ref":"SpendlyRepo7631E463"},":latest"]]},"name":"spendly","portMappings":[{"containerPort":5000,"protocol":"tcp"}],"logConfiguration":{"logDriver":"awslogs","options":{"awslogs-group":{"Ref":"SpendlyLogsC9368AC9"},"awslogs-stream-prefix":"spendly","awslogs-region":"us-east-1"}},"environment":[{"name":"NODE_ENV","value":"production"},{"name":"PORT","value":"5000"},{"name":"APP_URL","value":"https://app.spendlymanager.com"},{"name":"AWS_REGION","value":"us-east-1"},{"name":"AWS_SES_FROM_EMAIL","value":"noreply@spendlymanager.com"},{"name":"AWS_SES_FROM_NAME","value":"Spendly"},{"name":"AWS_SNS_SENDER_ID","value":"Spendly"}],"secrets":[{"name":"DATABASE_URL","valueFrom":{"Fn::Join":["",[{"Ref":"SpendlySecrets32749308"},":DATABASE_URL::"]]}},{"name":"SESSION_SECRET","valueFrom":{"Fn::Join":["",[{"Ref":"SpendlySecrets32749308"},":SESSION_SECRET::"]]}},{"name":"STRIPE_SECRET_KEY","valueFrom":{"Fn::Join":["",[{"Ref":"SpendlySecrets32749308"},":STRIPE_SECRET_KEY::"]]}},{"name":"STRIPE_WEBHOOK_SECRET","valueFrom":{"Fn::Join":["",[{"Ref":"SpendlySecrets32749308"},":STRIPE_WEBHOOK_SECRET::"]]}},{"name":"PAYSTACK_SECRET_KEY","valueFrom":{"Fn::Join":["",[{"Ref":"SpendlySecrets32749308"},":PAYSTACK_SECRET_KEY::"]]}},{"name":"COGNITO_USER_POOL_ID","valueFrom":{"Fn::Join":["",[{"Ref":"SpendlySecrets32749308"},":COGNITO_USER_POOL_ID::"]]}},{"name":"COGNITO_CLIENT_ID","valueFrom":{"Fn::Join":["",[{"Ref":"SpendlySecrets32749308"},":COGNITO_CLIENT_ID::"]]}}],"healthCheck":{"command":["CMD-SHELL","wget -qO- http://localhost:5000/api/health || exit 1"],"interval":30,"retries":3,"startPeriod":30,"timeout":5}}],"cpu":"512","executionRoleArn":{"Fn::GetAtt":["SpendlyTaskExecutionRoleB6DD6283","Arn"]},"family":"SpendlyStackSpendlyTask29C72C2E","memory":"1024","networkMode":"awsvpc","requiresCompatibilities":["FARGATE"],"taskRoleArn":{"Fn::GetAtt":["SpendlyTaskRole81FA43D9","Arn"]}}}},"spendly":{"id":"spendly","path":"SpendlyStack/SpendlyTask/spendly","constructInfo":{"fqn":"aws-cdk-lib.aws_ecs.ContainerDefinition","version":"2.240.0"}},"ExecutionRole":{"id":"ExecutionRole","path":"SpendlyStack/SpendlyTask/ExecutionRole","constructInfo":{"fqn":"aws-cdk-lib.aws_iam.Role","version":"2.240.0"},"children":{"Resource":{"id":"Resource","path":"SpendlyStack/SpendlyTask/ExecutionRole/Resource","constructInfo":{"fqn":"aws-cdk-lib.aws_iam.CfnRole","version":"2.240.0"},"attributes":{"aws:cdk:cloudformation:type":"AWS::IAM::Role","aws:cdk:cloudformation:props":{"assumeRolePolicyDocument":{"Statement":[{"Action":"sts:AssumeRole","Effect":"Allow","Principal":{"Service":"ecs-tasks.amazonaws.com"}}],"Version":"2012-10-17"}}}},"DefaultPolicy":{"id":"DefaultPolicy","path":"SpendlyStack/SpendlyTask/ExecutionRole/DefaultPolicy","constructInfo":{"fqn":"aws-cdk-lib.aws_iam.Policy","version":"2.240.0"},"children":{"Resource":{"id":"Resource","path":"SpendlyStack/SpendlyTask/ExecutionRole/DefaultPolicy/Resource","constructInfo":{"fqn":"aws-cdk-lib.aws_iam.CfnPolicy","version":"2.240.0"},"attributes":{"aws:cdk:cloudformation:type":"AWS::IAM::Policy","aws:cdk:cloudformation:props":{"policyDocument":{"Statement":[{"Action":["ecr:BatchCheckLayerAvailability","ecr:GetDownloadUrlForLayer","ecr:BatchGetImage"],"Effect":"Allow","Resource":{"Fn::GetAtt":["SpendlyRepo7631E463","Arn"]}},{"Action":"ecr:GetAuthorizationToken","Effect":"Allow","Resource":"*"},{"Action":["logs:CreateLogStream","logs:PutLogEvents"],"Effect":"Allow","Resource":{"Fn::GetAtt":["SpendlyLogsC9368AC9","Arn"]}},{"Action":["secretsmanager:GetSecretValue","secretsmanager:DescribeSecret"],"Effect":"Allow","Resource":{"Ref":"SpendlySecrets32749308"}}],"Version":"2012-10-17"},"policyName":"SpendlyTaskExecutionRoleDefaultPolicy61EEBFC4","roles":[{"Ref":"SpendlyTaskExecutionRoleB6DD6283"}]}}}}}}}}},"SpendlyLogs":{"id":"SpendlyLogs","path":"SpendlyStack/SpendlyLogs","constructInfo":{"fqn":"aws-cdk-lib.aws_logs.LogGroup","version":"2.240.0"},"children":{"Resource":{"id":"Resource","path":"SpendlyStack/SpendlyLogs/Resource","constructInfo":{"fqn":"aws-cdk-lib.aws_logs.CfnLogGroup","version":"2.240.0"},"attributes":{"aws:cdk:cloudformation:type":"AWS::Logs::LogGroup","aws:cdk:cloudformation:props":{"logGroupName":"/ecs/spendly","retentionInDays":30}}}}},"AlbSecurityGroup":{"id":"AlbSecurityGroup","path":"SpendlyStack/AlbSecurityGroup","constructInfo":{"fqn":"aws-cdk-lib.aws_ec2.SecurityGroup","version":"2.240.0"},"children":{"Resource":{"id":"Resource","path":"SpendlyStack/AlbSecurityGroup/Resource","constructInfo":{"fqn":"aws-cdk-lib.aws_ec2.CfnSecurityGroup","version":"2.240.0"},"attributes":{"aws:cdk:cloudformation:type":"AWS::EC2::SecurityGroup","aws:cdk:cloudformation:props":{"groupDescription":"Security group for Spendly ALB","securityGroupEgress":[{"cidrIp":"0.0.0.0/0","description":"Allow all outbound traffic by default","ipProtocol":"-1"}],"securityGroupIngress":[{"cidrIp":"0.0.0.0/0","ipProtocol":"tcp","fromPort":80,"toPort":80,"description":"Allow HTTP"},{"cidrIp":"0.0.0.0/0","ipProtocol":"tcp","fromPort":443,"toPort":443,"description":"Allow HTTPS"}],"vpcId":{"Ref":"SpendlyVpcAA2F8862"}}}}}},"SpendlyAlb":{"id":"SpendlyAlb","path":"SpendlyStack/SpendlyAlb","constructInfo":{"fqn":"aws-cdk-lib.aws_elasticloadbalancingv2.ApplicationLoadBalancer","version":"2.240.0"},"children":{"Resource":{"id":"Resource","path":"SpendlyStack/SpendlyAlb/Resource","constructInfo":{"fqn":"aws-cdk-lib.aws_elasticloadbalancingv2.CfnLoadBalancer","version":"2.240.0"},"attributes":{"aws:cdk:cloudformation:type":"AWS::ElasticLoadBalancingV2::LoadBalancer","aws:cdk:cloudformation:props":{"loadBalancerAttributes":[{"key":"deletion_protection.enabled","value":"false"}],"scheme":"internet-facing","securityGroups":[{"Fn::GetAtt":["AlbSecurityGroup86A59E99","GroupId"]}],"subnets":[{"Ref":"SpendlyVpcPublicSubnet1Subnet2F7967E4"},{"Ref":"SpendlyVpcPublicSubnet2SubnetF79DECBC"}],"type":"application"}}},"HttpListener":{"id":"HttpListener","path":"SpendlyStack/SpendlyAlb/HttpListener","constructInfo":{"fqn":"aws-cdk-lib.aws_elasticloadbalancingv2.ApplicationListener","version":"2.240.0"},"children":{"Resource":{"id":"Resource","path":"SpendlyStack/SpendlyAlb/HttpListener/Resource","constructInfo":{"fqn":"aws-cdk-lib.aws_elasticloadbalancingv2.CfnListener","version":"2.240.0"},"attributes":{"aws:cdk:cloudformation:type":"AWS::ElasticLoadBalancingV2::Listener","aws:cdk:cloudformation:props":{"defaultActions":[{"type":"forward","targetGroupArn":{"Ref":"SpendlyTargetGroup19DCE39A"}}],"loadBalancerArn":{"Ref":"SpendlyAlb7E0A90D4"},"port":80,"protocol":"HTTP"}}}}}}},"ServiceSecurityGroup":{"id":"ServiceSecurityGroup","path":"SpendlyStack/ServiceSecurityGroup","constructInfo":{"fqn":"aws-cdk-lib.aws_ec2.SecurityGroup","version":"2.240.0"},"children":{"Resource":{"id":"Resource","path":"SpendlyStack/ServiceSecurityGroup/Resource","constructInfo":{"fqn":"aws-cdk-lib.aws_ec2.CfnSecurityGroup","version":"2.240.0"},"attributes":{"aws:cdk:cloudformation:type":"AWS::EC2::SecurityGroup","aws:cdk:cloudformation:props":{"groupDescription":"Security group for Spendly ECS service","securityGroupEgress":[{"cidrIp":"0.0.0.0/0","description":"Allow all outbound traffic by default","ipProtocol":"-1"}],"vpcId":{"Ref":"SpendlyVpcAA2F8862"}}}},"from SpendlyStackAlbSecurityGroup815586E1:5000":{"id":"from SpendlyStackAlbSecurityGroup815586E1:5000","path":"SpendlyStack/ServiceSecurityGroup/from SpendlyStackAlbSecurityGroup815586E1:5000","constructInfo":{"fqn":"aws-cdk-lib.aws_ec2.CfnSecurityGroupIngress","version":"2.240.0"},"attributes":{"aws:cdk:cloudformation:type":"AWS::EC2::SecurityGroupIngress","aws:cdk:cloudformation:props":{"description":"Allow from ALB","fromPort":5000,"groupId":{"Fn::GetAtt":["ServiceSecurityGroup61DE1A49","GroupId"]},"ipProtocol":"tcp","sourceSecurityGroupId":{"Fn::GetAtt":["AlbSecurityGroup86A59E99","GroupId"]},"toPort":5000}}}}},"SpendlyService":{"id":"SpendlyService","path":"SpendlyStack/SpendlyService","constructInfo":{"fqn":"aws-cdk-lib.aws_ecs.FargateService","version":"2.240.0"},"children":{"Service":{"id":"Service","path":"SpendlyStack/SpendlyService/Service","constructInfo":{"fqn":"aws-cdk-lib.aws_ecs.CfnService","version":"2.240.0"},"attributes":{"aws:cdk:cloudformation:type":"AWS::ECS::Service","aws:cdk:cloudformation:props":{"cluster":{"Ref":"SpendlyClusterFEF95140"},"deploymentConfiguration":{"maximumPercent":200,"minimumHealthyPercent":50,"deploymentCircuitBreaker":{"enable":true,"rollback":true},"alarms":{"alarmNames":[],"enable":false,"rollback":false}},"deploymentController":{"type":"ECS"},"desiredCount":0,"enableEcsManagedTags":false,"healthCheckGracePeriodSeconds":60,"launchType":"FARGATE","loadBalancers":[{"targetGroupArn":{"Ref":"SpendlyTargetGroup19DCE39A"},"containerName":"spendly","containerPort":5000}],"networkConfiguration":{"awsvpcConfiguration":{"assignPublicIp":"DISABLED","subnets":[{"Ref":"SpendlyVpcPrivateSubnet1SubnetF34C9517"},{"Ref":"SpendlyVpcPrivateSubnet2Subnet8C4D6774"}],"securityGroups":[{"Fn::GetAtt":["ServiceSecurityGroup61DE1A49","GroupId"]}]}},"taskDefinition":{"Ref":"SpendlyTaskBA995AE1"}}}},"ScalingRole":{"id":"ScalingRole","path":"SpendlyStack/SpendlyService/ScalingRole","constructInfo":{"fqn":"aws-cdk-lib.Resource","version":"2.240.0"}},"TaskCount":{"id":"TaskCount","path":"SpendlyStack/SpendlyService/TaskCount","constructInfo":{"fqn":"aws-cdk-lib.aws_ecs.ScalableTaskCount","version":"2.240.0"},"children":{"Target":{"id":"Target","path":"SpendlyStack/SpendlyService/TaskCount/Target","constructInfo":{"fqn":"aws-cdk-lib.aws_applicationautoscaling.ScalableTarget","version":"2.240.0"},"children":{"Resource":{"id":"Resource","path":"SpendlyStack/SpendlyService/TaskCount/Target/Resource","constructInfo":{"fqn":"aws-cdk-lib.aws_applicationautoscaling.CfnScalableTarget","version":"2.240.0"},"attributes":{"aws:cdk:cloudformation:type":"AWS::ApplicationAutoScaling::ScalableTarget","aws:cdk:cloudformation:props":{"maxCapacity":4,"minCapacity":1,"resourceId":{"Fn::Join":["",["service/",{"Ref":"SpendlyClusterFEF95140"},"/",{"Fn::GetAtt":["SpendlyService958E8A1F","Name"]}]]},"roleArn":{"Fn::Join":["",["arn:",{"Ref":"AWS::Partition"},":iam::677343720858:role/aws-service-role/ecs.application-autoscaling.amazonaws.com/AWSServiceRoleForApplicationAutoScaling_ECSService"]]},"scalableDimension":"ecs:service:DesiredCount","serviceNamespace":"ecs"}}},"CpuScaling":{"id":"CpuScaling","path":"SpendlyStack/SpendlyService/TaskCount/Target/CpuScaling","constructInfo":{"fqn":"aws-cdk-lib.aws_applicationautoscaling.TargetTrackingScalingPolicy","version":"2.240.0"},"children":{"Resource":{"id":"Resource","path":"SpendlyStack/SpendlyService/TaskCount/Target/CpuScaling/Resource","constructInfo":{"fqn":"aws-cdk-lib.aws_applicationautoscaling.CfnScalingPolicy","version":"2.240.0"},"attributes":{"aws:cdk:cloudformation:type":"AWS::ApplicationAutoScaling::ScalingPolicy","aws:cdk:cloudformation:props":{"policyName":"SpendlyStackSpendlyServiceTaskCountTargetCpuScaling6E8788B6","policyType":"TargetTrackingScaling","scalingTargetId":{"Ref":"SpendlyServiceTaskCountTarget7CB88B71"},"targetTrackingScalingPolicyConfiguration":{"predefinedMetricSpecification":{"predefinedMetricType":"ECSServiceAverageCPUUtilization"},"scaleInCooldown":300,"scaleOutCooldown":60,"targetValue":70}}}}}}}}}}}},"SpendlyTargetGroup":{"id":"SpendlyTargetGroup","path":"SpendlyStack/SpendlyTargetGroup","constructInfo":{"fqn":"aws-cdk-lib.aws_elasticloadbalancingv2.ApplicationTargetGroup","version":"2.240.0"},"children":{"Resource":{"id":"Resource","path":"SpendlyStack/SpendlyTargetGroup/Resource","constructInfo":{"fqn":"aws-cdk-lib.aws_elasticloadbalancingv2.CfnTargetGroup","version":"2.240.0"},"attributes":{"aws:cdk:cloudformation:type":"AWS::ElasticLoadBalancingV2::TargetGroup","aws:cdk:cloudformation:props":{"healthCheckIntervalSeconds":30,"healthCheckPath":"/api/health","healthCheckTimeoutSeconds":5,"healthyThresholdCount":2,"port":5000,"protocol":"HTTP","targetGroupAttributes":[{"key":"deregistration_delay.timeout_seconds","value":"30"},{"key":"stickiness.enabled","value":"false"}],"targetType":"ip","unhealthyThresholdCount":3,"vpcId":{"Ref":"SpendlyVpcAA2F8862"}}}}}},"AlbDnsName":{"id":"AlbDnsName","path":"SpendlyStack/AlbDnsName","constructInfo":{"fqn":"aws-cdk-lib.CfnOutput","version":"2.240.0"}},"EcrRepositoryUri":{"id":"EcrRepositoryUri","path":"SpendlyStack/EcrRepositoryUri","constructInfo":{"fqn":"aws-cdk-lib.CfnOutput","version":"2.240.0"}},"ClusterName":{"id":"ClusterName","path":"SpendlyStack/ClusterName","constructInfo":{"fqn":"aws-cdk-lib.CfnOutput","version":"2.240.0"}},"ServiceName":{"id":"ServiceName","path":"SpendlyStack/ServiceName","constructInfo":{"fqn":"aws-cdk-lib.CfnOutput","version":"2.240.0"}},"DatabaseEndpoint":{"id":"DatabaseEndpoint","path":"SpendlyStack/DatabaseEndpoint","constructInfo":{"fqn":"aws-cdk-lib.CfnOutput","version":"2.240.0"}},"CDKMetadata":{"id":"CDKMetadata","path":"SpendlyStack/CDKMetadata","constructInfo":{"fqn":"constructs.Construct","version":"10.5.1"},"children":{"Default":{"id":"Default","path":"SpendlyStack/CDKMetadata/Default","constructInfo":{"fqn":"aws-cdk-lib.CfnResource","version":"2.240.0"}}}},"BootstrapVersion":{"id":"BootstrapVersion","path":"SpendlyStack/BootstrapVersion","constructInfo":{"fqn":"aws-cdk-lib.CfnParameter","version":"2.240.0"}},"CheckBootstrapVersion":{"id":"CheckBootstrapVersion","path":"SpendlyStack/CheckBootstrapVersion","constructInfo":{"fqn":"aws-cdk-lib.CfnRule","version":"2.240.0"}}}},"Tree":{"id":"Tree","path":"Tree","constructInfo":{"fqn":"constructs.Construct","version":"10.5.1"}}}}}